data_engineering_pulumi_components/__init__.py
data_engineering_pulumi_components/auth0/__init__.py
data_engineering_pulumi_components/auth0/create_application.py
data_engineering_pulumi_components/aws/__init__.py
data_engineering_pulumi_components/aws/buckets/bucket.py
data_engineering_pulumi_components/aws/buckets/cloudtrail_log_bucket.py
data_engineering_pulumi_components/aws/buckets/curated_bucket.py
data_engineering_pulumi_components/aws/buckets/fail_bucket.py
data_engineering_pulumi_components/aws/buckets/landing_bucket.py
data_engineering_pulumi_components/aws/buckets/pulumi_backend_bucket.py
data_engineering_pulumi_components/aws/buckets/raw_history_bucket.py
data_engineering_pulumi_components/aws/cloud_trail/cloud_trail.py
data_engineering_pulumi_components/aws/glue/glue_job.py
data_engineering_pulumi_components/aws/glue/glue_move_script.py
data_engineering_pulumi_components/aws/lambdas/authorisation_function.py
data_engineering_pulumi_components/aws/lambdas/copy_object_function.py
data_engineering_pulumi_components/aws/lambdas/get_databases_function.py
data_engineering_pulumi_components/aws/lambdas/get_tables_function.py
data_engineering_pulumi_components/aws/lambdas/lambda_handlers/authorise_/authorise_.py
data_engineering_pulumi_components/aws/lambdas/lambda_handlers/copy/copy_.py
data_engineering_pulumi_components/aws/lambdas/lambda_handlers/get_databases/get_databases.py
data_engineering_pulumi_components/aws/lambdas/lambda_handlers/get_tables/get_tables.py
data_engineering_pulumi_components/aws/lambdas/lambda_handlers/move/move.py
data_engineering_pulumi_components/aws/lambdas/lambda_handlers/notify/notify_lambda_failure.py
data_engineering_pulumi_components/aws/lambdas/lambda_handlers/upload_/upload_.py
data_engineering_pulumi_components/aws/lambdas/lambda_handlers/validate/dependencies.tar.gz
data_engineering_pulumi_components/aws/lambdas/lambda_handlers/validate/validate.py
data_engineering_pulumi_components/aws/lambdas/move_object_function.py
data_engineering_pulumi_components-0.4.1.dist-info/WHEEL
data_engineering_pulumi_components-0.4.1.dist-info/METADATA
data_engineering_pulumi_components-0.4.1.dist-info/RECORD
