Metadata-Version: 2.1
Name: data-engineering-pulumi-components
Version: 0.4.1
Summary: Reusable components for use in Pulumi Python projects
License: MIT
Author: MoJ Data Engineering Team
Author-email: data-engineering@digital.justice.gov.uk
Requires-Python: >=3.8,<4.0
Classifier: License :: OSI Approved :: MIT License
Classifier: Programming Language :: Python :: 3
Classifier: Programming Language :: Python :: 3.10
Classifier: Programming Language :: Python :: 3.8
Classifier: Programming Language :: Python :: 3.9
Requires-Dist: boto3 (>=1.17.00,<2.0.0)
Requires-Dist: protobuf (>=4.21.5,<5.0.0)
Requires-Dist: pulumi (>=3.38.0,<4.0.0)
Requires-Dist: pulumi-auth0 (>=2.12.0,<3.0.0)
Requires-Dist: pulumi-aws (>=5.0.0,<6.0.0)
